geoh5_interop/__init__.py
geoh5_interop/_version.py
geoh5_interop-1.3.0.dist-info/METADATA
geoh5_interop-1.3.0.dist-info/WHEEL
geoh5_interop-1.3.0.dist-info/licenses/LICENSE
geoh5_interop-1.3.0.dist-info/RECORD
