Metadata-Version: 2.4
Name: geoh5-interop
Version: 1.3.0
Summary: A meta-package that groups together packages for interoperability between GEOH5 and other file formats.
License-Expression: MIT
License-File: LICENSE
Keywords: data format,data,earth science,open science,geoh5,geology,geophysics,geoscience,interoperability,io,lasio,las-files,log-ascii-standard,mining,well-logs,wireline,well-log
Author: Mira Geoscience
Author-email: support@mirageoscience.com
Requires-Python: >=3.10,<4.0
Classifier: Development Status :: 4 - Beta
Classifier: Intended Audience :: Developers
Classifier: Intended Audience :: Science/Research
Classifier: Natural Language :: English
Classifier: Programming Language :: Python :: 3
Classifier: Programming Language :: Python :: 3.10
Classifier: Programming Language :: Python :: 3.11
Classifier: Programming Language :: Python :: 3.12
Classifier: Programming Language :: Python :: 3.13
Classifier: Programming Language :: Python :: 3.14
Classifier: Topic :: Database
Classifier: Topic :: Scientific/Engineering
Classifier: Topic :: Scientific/Engineering :: Mathematics
Classifier: Topic :: Scientific/Engineering :: Physics
Classifier: Topic :: Software Development :: Libraries :: Python Modules
Requires-Dist: geoh5py (>=0.12.0rc2,<0.13.dev0)
Requires-Dist: las-geoh5 (>=0.3.2rc1,<0.4.dev0)
Requires-Dist: mira-omf (>=3.3.2rc1,<3.4.dev0)
Project-URL: Homepage, https://www.mirageoscience.com/mining-industry-software/python-integration/
Project-URL: Repository, https://github.com/MiraGeoscience/geoh5py-interop
